odoo10_addon_account_reconcile_structured_ref_auto-10.0.1.0.0.99.dev4-py3.8-nspkg.pth
odoo/addons/account_reconcile_structured_ref_auto/README.rst
odoo/addons/account_reconcile_structured_ref_auto/__init__.py
odoo/addons/account_reconcile_structured_ref_auto/__manifest__.py
odoo/addons/account_reconcile_structured_ref_auto/i18n/account_reconcile_structured_ref_auto.pot
odoo/addons/account_reconcile_structured_ref_auto/models/__init__.py
odoo/addons/account_reconcile_structured_ref_auto/models/account_bank_statement_line.py
odoo/addons/account_reconcile_structured_ref_auto/readme/CONTRIBUTORS.rst
odoo/addons/account_reconcile_structured_ref_auto/readme/DESCRIPTION.rst
odoo/addons/account_reconcile_structured_ref_auto/readme/USAGE.rst
odoo/addons/account_reconcile_structured_ref_auto/static/description/icon.png
odoo/addons/account_reconcile_structured_ref_auto/static/description/index.html
odoo/addons/account_reconcile_structured_ref_auto/static/src/js/account_reconciliation.js
odoo/addons/account_reconcile_structured_ref_auto/static/src/xml/account_reconciliation.xml
odoo/addons/account_reconcile_structured_ref_auto/views/assets.xml
odoo10_addon_account_reconcile_structured_ref_auto-10.0.1.0.0.99.dev4.dist-info/METADATA
odoo10_addon_account_reconcile_structured_ref_auto-10.0.1.0.0.99.dev4.dist-info/WHEEL
odoo10_addon_account_reconcile_structured_ref_auto-10.0.1.0.0.99.dev4.dist-info/namespace_packages.txt
odoo10_addon_account_reconcile_structured_ref_auto-10.0.1.0.0.99.dev4.dist-info/top_level.txt
odoo10_addon_account_reconcile_structured_ref_auto-10.0.1.0.0.99.dev4.dist-info/RECORD
